{
  "project_info": {
    "project_number": "706833710872",
    "firebase_url": "https://teammangementsystem-default-rtdb.asia-southeast1.firebasedatabase.app",
    "project_id": "teammangementsystem",
    "storage_bucket": "teammangementsystem.appspot.com"
  },
  "client": [
    {
      "client_info": {
        "mobilesdk_app_id": "1:706833710872:android:3c5e66b89c28460d1f686d",
        "android_client_info": {
          "package_name": "com.team.managemet.sysytem"
        }
      },
      "oauth_client": [
        {
          "client_id": "706833710872-650l00kaeibdovtp4m0le4tb4ogrln7n.apps.googleusercontent.com",
          "client_type": 1,
          "android_info": {
            "package_name": "com.team.managemet.sysytem",
            "certificate_hash": "9bbb3186b2189ef16d8f272bdab59362c395cbb4"
          }
        },
        {
          "client_id": "706833710872-8ao3b8613o05f8rssfkrlrnpid01rgl0.apps.googleusercontent.com",
          "client_type": 3
        }
      ],
      "api_key": [
        {
          "current_key": "AIzaSyCFbiloxnO3ukNU7pok-GStb_CZeYZHOws"
        }
      ],
      "services": {
        "appinvite_service": {
          "other_platform_oauth_client": [
            {
              "client_id": "706833710872-8ao3b8613o05f8rssfkrlrnpid01rgl0.apps.googleusercontent.com",
              "client_type": 3
            },
            {
              "client_id": "706833710872-t0tqvbur54kda0frthd17fhghlos2olh.apps.googleusercontent.com",
              "client_type": 2,
              "ios_info": {
                "bundle_id": "com.team.managemet.sysytem"
              }
            }
          ]
        }
      }
    },
    {
      "client_info": {
        "mobilesdk_app_id": "1:706833710872:android:f8bba8be654e8e6f1f686d",
        "android_client_info": {
          "package_name": "com.tms.app.tms_app"
        }
      },
      "oauth_client": [
        {
          "client_id": "706833710872-8ao3b8613o05f8rssfkrlrnpid01rgl0.apps.googleusercontent.com",
          "client_type": 3
        }
      ],
      "api_key": [
        {
          "current_key": "AIzaSyCFbiloxnO3ukNU7pok-GStb_CZeYZHOws"
        }
      ],
      "services": {
        "appinvite_service": {
          "other_platform_oauth_client": [
            {
              "client_id": "706833710872-8ao3b8613o05f8rssfkrlrnpid01rgl0.apps.googleusercontent.com",
              "client_type": 3
            },
            {
              "client_id": "706833710872-t0tqvbur54kda0frthd17fhghlos2olh.apps.googleusercontent.com",
              "client_type": 2,
              "ios_info": {
                "bundle_id": "com.team.managemet.sysytem"
              }
            }
          ]
        }
      }
    }
  ],
  "configuration_version": "1"
}